paperweights/__init__.py
paperweights/cli.py
paperweights/paperweights.py
paperweights-0.0.1.dist-info/AUTHORS.rst
paperweights-0.0.1.dist-info/LICENSE
paperweights-0.0.1.dist-info/METADATA
paperweights-0.0.1.dist-info/WHEEL
paperweights-0.0.1.dist-info/entry_points.txt
paperweights-0.0.1.dist-info/top_level.txt
paperweights-0.0.1.dist-info/RECORD
