Metadata-Version: 2.1
Name: paperweights
Version: 0.0.1
Summary: Easy to use implementations of papers
Home-page: https://github.com/OpenLake/paperweights
Author: OpenLake
Author-email: yatendras@iitbhilai.ac.in
License: GNU General Public License v3
Keywords: paperweights
Platform: UNKNOWN
Classifier: Development Status :: 2 - Pre-Alpha
Classifier: Intended Audience :: Developers
Classifier: License :: OSI Approved :: GNU General Public License v3 (GPLv3)
Classifier: Natural Language :: English
Classifier: Programming Language :: Python :: 3
Classifier: Programming Language :: Python :: 3.5
Classifier: Programming Language :: Python :: 3.6
Classifier: Programming Language :: Python :: 3.7
Classifier: Programming Language :: Python :: 3.8
Requires-Python: >=3.5
